montagu/__init__.py
montagu/montagu_api.py
test/__init__.py
test/test_montagu_api.py
montagu-0.0.3.dist-info/LICENSE
montagu-0.0.3.dist-info/METADATA
montagu-0.0.3.dist-info/WHEEL
montagu-0.0.3.dist-info/top_level.txt
montagu-0.0.3.dist-info/RECORD
