Metadata-Version: 2.1
Name: montagu
Version: 0.0.3
Summary: Python client for Montagu API
Home-page: https://github.com/vimc/montagu-py
Author: Emma Russell
Author-email: e.russell@imperial.ac.uk
License: MIT
Platform: UNKNOWN
Classifier: Programming Language :: Python :: 3
Classifier: License :: OSI Approved :: MIT License
Classifier: Operating System :: OS Independent
Requires-Dist: requests
Requires-Dist: pytest
